{
  "Changes": [
    {
      "Action": "EditData",
      "Target": "Data/Events/HaleyHouse",
      "Entries": {
        "BarleyZP.EnemyOfTheValley_HaleyNegative2/NegativeFriendship Haley -500/p Haley": "50s/6 20/farmer 2 23 0 Haley 12 20 3/move farmer 0 -3 1 Haley -7 0 3/speak Haley \"@? What are you doing here?\"/quickQuestion #I came to visit you#I came to see Emily.(break)speak Haley \"Why, finally here for some fashion advice?\"\\questionAnswered cameToSeeHaley(break)speak Haley \"Emily isn't going to give you the fashion advice you clearly need.$3\"/move Haley -2 0 3/faceDirection farmer 2/pause 500/faceDirection farmer 1/pause 500/emote farmer 8/speak Haley \"Your shirt and shoes don't match at all! Is this how all farmers are?\"/quickQuestion #Honestly, I've never thought a lot about my outfits.#Stop insulting me! I know how to dress!(break)speak Haley \"Great, you do understand you need help!$h\"(break)friendship Haley -20\\speak Haley \"I'm just being brutally honest. Someone had to tell you!\"/emote farmer 12/pause 500/fork cameToSeeHaley BarleyZP.EnemyOfTheValley_cameToSeeHaleySpeak/pause 1000/speak Haley \"Anyway, I've got things to do. Have fun with Emily.$3\"/faceDirection Haley 1/move Haley 7 0 3 true/globalFade/viewport -1000 -1000/end",
        "BarleyZP.EnemyOfTheValley_cameToSeeHaleySpeak": "speak Haley \"So anyway, did you need something else from me?\"/globalFade/viewport -1000 -1000/end"
      }
    }
  ]
}